seipy/__init__.py
seipy/base.py
seipy/jupyter_.py
seipy/s3_.py
seipy/ml/__init__.py
seipy/ml/linear_algebra.py
seipy/numpy_/__init__.py
seipy/numpy_/base.py
seipy/pandas_/__init__.py
seipy/pandas_/base.py
seipy/pcap/__init__.py
seipy/pcap/base.py
seipy/plots_/__init__.py
seipy/plots_/base.py
seipy/spark_/__init__.py
seipy/spark_/base.py
seipy-1.3.2.dist-info/DESCRIPTION.rst
seipy-1.3.2.dist-info/METADATA
seipy-1.3.2.dist-info/RECORD
seipy-1.3.2.dist-info/WHEEL
seipy-1.3.2.dist-info/metadata.json
seipy-1.3.2.dist-info/top_level.txt
