Metadata-Version: 2.0
Name: seipy
Version: 1.3.2
Summary: Helper functions for data science
Home-page: https://github.com/Seiji-Armstrong/seipy
Author: UNKNOWN
Author-email: seiji.armstrong@gmail.com
License: MIT
Keywords: pandas numpy spark jupyter data-science machine-learning s3
Platform: UNKNOWN
Classifier: Development Status :: 5 - Production/Stable
Classifier: Intended Audience :: Developers
Classifier: Topic :: Scientific/Engineering :: Artificial Intelligence
Classifier: License :: OSI Approved :: MIT License
Classifier: Programming Language :: Python :: 3
Classifier: Programming Language :: Python :: 3.4
Classifier: Programming Language :: Python :: 3.5
Classifier: Programming Language :: Python :: 3.6
Requires-Python: >=3
Requires-Dist: boto3
Requires-Dist: ipython
Requires-Dist: matplotlib
Requires-Dist: numpy
Requires-Dist: pandas
Requires-Dist: pandas
Requires-Dist: pyspark
Requires-Dist: scapy-python3
Requires-Dist: scikit-learn
Requires-Dist: scipy
Requires-Dist: seaborn
